[
  {
    "ytid": "PLWiCoZNyCaTNOh_6N0Q2_lRxP2YAGGA0N",
    "title": "I am American",
    "level": "Newbie",
    "fileUrl":
        "https://ia800100.us.archive.org/23/items/frenchpod/frenchpod_0001.pdf",
    "image": "https://i.ibb.co/CJ1457X/I-am-American.png",
    "list": []
  },
  {
    "ytid": "PLWiCoZNyCaTMFNfoniH0MtGc9oK5HDu2E",
    "title": "I'm cold",
    "level": "Newbie",
    "fileUrl":
        "https://ia800100.us.archive.org/23/items/frenchpod/frenchpod_0002.pdf",
    "image": "https://i.ibb.co/PYw2rnF/I-m-cold.webp",
    "list": []
  },
  {
    "ytid": "PLWiCoZNyCaTMrX3YqJM70UpYPKEtrF8eR",
    "title": "Bad Movie",
    "level": "Newbie",
    "fileUrl":
        "https://ia800100.us.archive.org/23/items/frenchpod/frenchpod_0003.pdf",
    "image": "https://i.ibb.co/qNcnNt4/Bad-Movie.png",
    "list": []
  },
  {
    "ytid": "PLWiCoZNyCaTNttE0FgQr9QKkPL9rwRJvh",
    "title": "Do you have a light?",
    "level": "Newbie",
    "fileUrl":
        "https://ia800100.us.archive.org/23/items/frenchpod/frenchpod_0004.pdf",
    "image": "https://i.ibb.co/ZL2d7DW/Do-you-have-a-light.png",
    "list": []
  }
]
